jidutest_framework/__init__.py
jidutest_framework-0.1.3.dist-info/METADATA
jidutest_framework-0.1.3.dist-info/WHEEL
jidutest_framework-0.1.3.dist-info/top_level.txt
jidutest_framework-0.1.3.dist-info/RECORD
