Metadata-Version: 2.1
Name: jidutest-framework
Version: 0.1.3
Summary: JiduTest framework
Home-page: UNKNOWN
Author: ee
Author-email: ee@jiduauto.com
License: MIT
Platform: UNKNOWN
